Metadata-Version: 1.0
Name: rkdist
Version: 0.1
Summary: Gaussian distributions and binomial distributions
Home-page: UNKNOWN
Author: Raj Kumar Kausik
Author-email: rrajkukausik@gmail.com
License: UNKNOWN
Platform: UNKNOWN
